SimpleLoggerV1/SimpleLoggerV1.py
SimpleLoggerV1/__init__.py
SimpleLoggerV1/main.py
simpleloggerv1-0.3.1.dist-info/METADATA
simpleloggerv1-0.3.1.dist-info/WHEEL
simpleloggerv1-0.3.1.dist-info/licenses/LICENSE
simpleloggerv1-0.3.1.dist-info/RECORD
